odoo/addons/project_purchase_link/README.rst
odoo/addons/project_purchase_link/__init__.py
odoo/addons/project_purchase_link/__manifest__.py
odoo/addons/project_purchase_link/i18n/es.po
odoo/addons/project_purchase_link/i18n/it.po
odoo/addons/project_purchase_link/i18n/project_purchase_link.pot
odoo/addons/project_purchase_link/i18n/pt_BR.po
odoo/addons/project_purchase_link/i18n/sl.po
odoo/addons/project_purchase_link/models/__init__.py
odoo/addons/project_purchase_link/models/project_project.py
odoo/addons/project_purchase_link/readme/CONTRIBUTORS.md
odoo/addons/project_purchase_link/readme/DESCRIPTION.md
odoo/addons/project_purchase_link/readme/USAGE.md
odoo/addons/project_purchase_link/static/description/icon.png
odoo/addons/project_purchase_link/static/description/index.html
odoo/addons/project_purchase_link/tests/__init__.py
odoo/addons/project_purchase_link/tests/test_project_purchase_link.py
odoo/addons/project_purchase_link/views/project_project_view.xml
odoo_addon_project_purchase_link-18.0.1.0.0.2.dist-info/METADATA
odoo_addon_project_purchase_link-18.0.1.0.0.2.dist-info/WHEEL
odoo_addon_project_purchase_link-18.0.1.0.0.2.dist-info/top_level.txt
odoo_addon_project_purchase_link-18.0.1.0.0.2.dist-info/RECORD
